{
  "name": "parsegraph-graphpainter",
  "version": "1.6.0",
  "description": "node",
  "main": "dist/parsegraph-graphpainter.js",
  "types": "dist/parsegraph-graphpainter.d.ts",
  "repository": {
    "type": "git",
    "url": "git+ssh://git@github.com/parsegraph/graphpainter.git"
  },
  "author": "Rainback, Inc.",
  "license": "MIT",
  "bugs": {
    "url": "https://github.com/parsegraph/graphpainter/issues"
  },
  "homepage": "https://github.com/parsegraph/graphpainter#readme",
  "dependencies": {
  }
}
